tornado_template_server
