Metadata-Version: 1.0
Name: tornado-template-server
Version: 0.0.5
Summary: Tornado Template Server for dynamically serving template data (includes data-uri uimodule)
Home-page: UNKNOWN
Author: Shane R. Spencer
Author-email: shane@bogomip.com
License: MIT
Platform: UNKNOWN
